{
	"credit": "Made with Blockbench",
	"textures": {
		"0": "block/lodowy",
		"particle": "block/lodowy"
	},
	"elements": [
		{
			"from": [7, 0, 7],
			"to": [8, 5, 8],
			"faces": {
				"north": {"uv": [3, 0, 4, 5], "texture": "#0"},
				"east": {"uv": [0, 4, 1, 9], "texture": "#0"},
				"south": {"uv": [4, 0, 5, 5], "texture": "#0"},
				"west": {"uv": [1, 4, 2, 9], "texture": "#0"},
				"up": {"uv": [3, 5, 2, 4], "texture": "#0"},
				"down": {"uv": [11, 2, 10, 3], "texture": "#0"}
			}
		},
		{
			"from": [7.01, 2.31913, 9.52238],
			"to": [7.99, 5.81913, 10.52238],
			"rotation": {"angle": -22.5, "axis": "x", "origin": [0, -2.68087, 2.52238]},
			"faces": {
				"north": {"uv": [2, 7, 3, 10.5], "texture": "#0"},
				"east": {"uv": [7, 2, 8, 5.5], "texture": "#0"},
				"south": {"uv": [3, 7, 4, 10.5], "texture": "#0"},
				"west": {"uv": [4, 7, 5, 10.5], "texture": "#0"},
				"up": {"uv": [13, 7, 12, 6], "texture": "#0"},
				"down": {"uv": [13, 7, 12, 8], "texture": "#0"}
			}
		},
		{
			"from": [7, 7.85089, 5.73673],
			"to": [8, 10.85089, 6.73673],
			"rotation": {"angle": 0, "axis": "y", "origin": [-0.01, -0.64911, -1.26327]},
			"faces": {
				"north": {"uv": [7, 6, 8, 9], "texture": "#0"},
				"east": {"uv": [8, 0, 9, 3], "texture": "#0"},
				"south": {"uv": [8, 3, 9, 6], "texture": "#0"},
				"west": {"uv": [5, 8, 6, 11], "texture": "#0"},
				"up": {"uv": [10, 13, 9, 12], "texture": "#0"},
				"down": {"uv": [11, 12, 10, 13], "texture": "#0"}
			}
		},
		{
			"from": [7.1, 14.50021, 1.39036],
			"to": [7.9, 17.50021, 2.39036],
			"rotation": {"angle": 22.5, "axis": "x", "origin": [-0.01, 1.75021, -5.60964]},
			"faces": {
				"north": {"uv": [6, 8, 7, 11], "texture": "#0"},
				"east": {"uv": [8, 6, 9, 9], "texture": "#0"},
				"south": {"uv": [0, 9, 1, 12], "texture": "#0"},
				"west": {"uv": [9, 0, 10, 3], "texture": "#0"},
				"up": {"uv": [13, 12, 12, 11], "texture": "#0"},
				"down": {"uv": [13, 12, 12, 13], "texture": "#0"}
			}
		},
		{
			"from": [7.3, 17.50021, 1.39036],
			"to": [7.7, 19.60021, 2.39036],
			"rotation": {"angle": 22.5, "axis": "x", "origin": [-0.01, 1.75021, -5.60964]},
			"faces": {
				"north": {"uv": [13, 0, 13.5, 2], "texture": "#0"},
				"east": {"uv": [1, 9, 2, 11], "texture": "#0"},
				"south": {"uv": [1, 13, 1.5, 15], "texture": "#0"},
				"west": {"uv": [7, 9, 8, 11], "texture": "#0"},
				"up": {"uv": [0.5, 16, 0, 15], "texture": "#0"},
				"down": {"uv": [15.5, 0, 15, 1], "texture": "#0"}
			}
		},
		{
			"from": [7.4, 26.00418, -3.51959],
			"to": [7.6, 28.10418, -2.51959],
			"rotation": {"angle": 45, "axis": "x", "origin": [-0.01, 7.25418, -10.51959]},
			"faces": {
				"north": {"uv": [2, 13, 2.5, 15], "texture": "#0"},
				"east": {"uv": [9, 7, 10, 9], "texture": "#0"},
				"south": {"uv": [13, 2, 13.5, 4], "texture": "#0"},
				"west": {"uv": [8, 9, 9, 11], "texture": "#0"},
				"up": {"uv": [1.5, 16, 1, 15], "texture": "#0"},
				"down": {"uv": [15.5, 1, 15, 2], "texture": "#0"}
			}
		},
		{
			"from": [7.425, 14.94761, 9.17334],
			"to": [7.575, 17.04761, 10.17334],
			"rotation": {"angle": 0, "axis": "y", "origin": [0.015, -7.05239, 11.27334]},
			"faces": {
				"north": {"uv": [3, 13, 3.5, 15], "texture": "#0"},
				"east": {"uv": [9, 9, 10, 11], "texture": "#0"},
				"south": {"uv": [4, 13, 4.5, 15], "texture": "#0"},
				"west": {"uv": [10, 0, 11, 2], "texture": "#0"},
				"up": {"uv": [2.5, 16, 2, 15], "texture": "#0"},
				"down": {"uv": [15.5, 2, 15, 3], "texture": "#0"}
			}
		},
		{
			"from": [7.443, 18.35691, 1.67619],
			"to": [7.573, 20.45691, 2.67619],
			"rotation": {"angle": 22.5, "axis": "x", "origin": [0.009, -1.14309, -7.42381]},
			"faces": {
				"north": {"uv": [13, 4, 13.5, 6], "texture": "#0"},
				"east": {"uv": [10, 7, 11, 9], "texture": "#0"},
				"south": {"uv": [5, 13, 5.5, 15], "texture": "#0"},
				"west": {"uv": [10, 9, 11, 11], "texture": "#0"},
				"up": {"uv": [3.5, 16, 3, 15], "texture": "#0"},
				"down": {"uv": [15.5, 3, 15, 4], "texture": "#0"}
			}
		},
		{
			"from": [7.425, 11.29014, 8.44582],
			"to": [7.575, 13.39014, 9.44582],
			"rotation": {"angle": 0, "axis": "y", "origin": [0.013, -6.80986, 10.54582]},
			"faces": {
				"north": {"uv": [6, 13, 6.5, 15], "texture": "#0"},
				"east": {"uv": [11, 0, 12, 2], "texture": "#0"},
				"south": {"uv": [13, 6, 13.5, 8], "texture": "#0"},
				"west": {"uv": [1, 11, 2, 13], "texture": "#0"},
				"up": {"uv": [4.5, 16, 4, 15], "texture": "#0"},
				"down": {"uv": [15.5, 4, 15, 5], "texture": "#0"}
			}
		},
		{
			"from": [7.42, 11.36014, 15.15514],
			"to": [7.59, 13.46014, 16.15514],
			"rotation": {"angle": -22.5, "axis": "x", "origin": [0.013, -4.48986, 17.25514]},
			"faces": {
				"north": {"uv": [13, 8, 13.5, 10], "texture": "#0"},
				"east": {"uv": [2, 11, 3, 13], "texture": "#0"},
				"south": {"uv": [9, 13, 9.5, 15], "texture": "#0"},
				"west": {"uv": [11, 2, 12, 4], "texture": "#0"},
				"up": {"uv": [5.5, 16, 5, 15], "texture": "#0"},
				"down": {"uv": [15.5, 5, 15, 6], "texture": "#0"}
			}
		},
		{
			"from": [7.421, 7.63268, 9.17334],
			"to": [7.571, 9.73268, 10.17334],
			"rotation": {"angle": 0, "axis": "y", "origin": [0.028, -6.56732, 10.34834]},
			"faces": {
				"north": {"uv": [10, 13, 10.5, 15], "texture": "#0"},
				"east": {"uv": [3, 11, 4, 13], "texture": "#0"},
				"south": {"uv": [13, 10, 13.5, 12], "texture": "#0"},
				"west": {"uv": [4, 11, 5, 13], "texture": "#0"},
				"up": {"uv": [6.5, 16, 6, 15], "texture": "#0"},
				"down": {"uv": [15.5, 6, 15, 7], "texture": "#0"}
			}
		},
		{
			"from": [7.396, 6.3852, 3.78332],
			"to": [7.596, 8.6352, 4.78332],
			"rotation": {"angle": 22.5, "axis": "x", "origin": [0.028, -5.4148, 4.95832]},
			"faces": {
				"north": {"uv": [12, 13, 12.5, 15], "texture": "#0"},
				"east": {"uv": [11, 4, 12, 6], "texture": "#0"},
				"south": {"uv": [13, 12, 13.5, 14], "texture": "#0"},
				"west": {"uv": [5, 11, 6, 13], "texture": "#0"},
				"up": {"uv": [15.5, 8, 15, 7], "texture": "#0"},
				"down": {"uv": [15.5, 8, 15, 9], "texture": "#0"}
			}
		},
		{
			"from": [7.346, 6.98457, -0.25959],
			"to": [7.646, 8.95957, 0.74041],
			"rotation": {"angle": 45, "axis": "x", "origin": [0.028, -3.09043, 0.91541]},
			"faces": {
				"north": {"uv": [14, 0, 14.5, 2], "texture": "#0"},
				"east": {"uv": [6, 11, 7, 13], "texture": "#0"},
				"south": {"uv": [14, 2, 14.5, 4], "texture": "#0"},
				"west": {"uv": [11, 6, 12, 8], "texture": "#0"},
				"up": {"uv": [9.5, 16, 9, 15], "texture": "#0"},
				"down": {"uv": [15.5, 9, 15, 10], "texture": "#0"}
			}
		},
		{
			"from": [7.425, 14.94761, 8.47334],
			"to": [7.575, 15.74761, 9.17334],
			"rotation": {"angle": 0, "axis": "y", "origin": [0.015, -7.05239, 11.27334]},
			"faces": {
				"north": {"uv": [10, 15, 10.5, 16], "texture": "#0"},
				"east": {"uv": [15, 10, 15.5, 11], "texture": "#0"},
				"south": {"uv": [15, 11, 15.5, 12], "texture": "#0"},
				"west": {"uv": [12, 15, 12.5, 16], "texture": "#0"},
				"up": {"uv": [15.5, 12.5, 15, 12], "texture": "#0"},
				"down": {"uv": [15.5, 13, 15, 13.5], "texture": "#0"}
			}
		},
		{
			"from": [7.393, 18.35691, 1.07619],
			"to": [7.623, 20.05691, 1.67619],
			"rotation": {"angle": 22.5, "axis": "x", "origin": [0.009, -1.14309, -7.42381]},
			"faces": {
				"north": {"uv": [14, 8, 14.5, 9.5], "texture": "#0"},
				"east": {"uv": [14, 10, 14.5, 11.5], "texture": "#0"},
				"south": {"uv": [11, 14, 11.5, 15.5], "texture": "#0"},
				"west": {"uv": [14, 12, 14.5, 13.5], "texture": "#0"},
				"up": {"uv": [15.5, 14.5, 15, 14], "texture": "#0"},
				"down": {"uv": [15.5, 15, 15, 15.5], "texture": "#0"}
			}
		},
		{
			"from": [7.375, 11.29014, 6.94582],
			"to": [7.65, 13.61514, 8.44582],
			"rotation": {"angle": 0, "axis": "y", "origin": [0.013, -6.80986, 10.54582]},
			"faces": {
				"north": {"uv": [11, 11, 11.5, 13.5], "texture": "#0"},
				"east": {"uv": [5, 2, 6.5, 4.5], "texture": "#0"},
				"south": {"uv": [0, 12, 0.5, 14.5], "texture": "#0"},
				"west": {"uv": [5, 5, 6.5, 7.5], "texture": "#0"},
				"up": {"uv": [13.5, 15.5, 13, 14], "texture": "#0"},
				"down": {"uv": [14.5, 14, 14, 15.5], "texture": "#0"}
			}
		},
		{
			"from": [7.32, 11.36014, 12.30514],
			"to": [7.69, 13.46014, 15.15514],
			"rotation": {"angle": -22.5, "axis": "x", "origin": [0.013, -4.48986, 17.25514]},
			"faces": {
				"north": {"uv": [14, 4, 14.5, 6], "texture": "#0"},
				"east": {"uv": [0, 0, 3, 2], "texture": "#0"},
				"south": {"uv": [14, 6, 14.5, 8], "texture": "#0"},
				"west": {"uv": [0, 2, 3, 4], "texture": "#0"},
				"up": {"uv": [7.5, 14, 7, 11], "texture": "#0"},
				"down": {"uv": [8.5, 11, 8, 14], "texture": "#0"}
			}
		},
		{
			"from": [7.396, 6.4352, 1.33332],
			"to": [7.596, 8.6352, 3.78332],
			"rotation": {"angle": 22.5, "axis": "x", "origin": [0.028, -5.4148, 4.95832]},
			"faces": {
				"north": {"uv": [7, 14, 7.5, 16], "texture": "#0"},
				"east": {"uv": [5, 0, 7.5, 2], "texture": "#0"},
				"south": {"uv": [8, 14, 8.5, 16], "texture": "#0"},
				"west": {"uv": [2, 5, 4.5, 7], "texture": "#0"},
				"up": {"uv": [12.5, 2.5, 12, 0], "texture": "#0"},
				"down": {"uv": [12.5, 3, 12, 5.5], "texture": "#0"}
			}
		},
		{
			"from": [6.8, -0.75, 6.8],
			"to": [8.2, 0, 8.2],
			"faces": {
				"north": {"uv": [11, 8, 12.5, 9], "texture": "#0"},
				"east": {"uv": [9, 11, 10.5, 12], "texture": "#0"},
				"south": {"uv": [11, 9, 12.5, 10], "texture": "#0"},
				"west": {"uv": [11, 10, 12.5, 11], "texture": "#0"},
				"up": {"uv": [10.5, 4.5, 9, 3], "texture": "#0"},
				"down": {"uv": [10.5, 5, 9, 6.5], "texture": "#0"}
			}
		}
	],
	"display": {
		"thirdperson_righthand": {
			"rotation": [174.5, 0, 0],
			"translation": [0, -7.25, 1.25]
		},
		"thirdperson_lefthand": {
			"rotation": [-179.25, 0, 0],
			"translation": [-0.75, -7.5, 0.5]
		},
		"firstperson_righthand": {
			"rotation": [171.71, 17.9, -179.98],
			"translation": [2.5, 4.75, -0.5]
		},
		"firstperson_lefthand": {
			"rotation": [-175.93, 16, 165.44],
			"translation": [2.5, 5.5, 0]
		},
		"ground": {
			"rotation": [0, 0, -90],
			"translation": [0, -2.25, 0]
		},
		"gui": {
			"rotation": [90, -46.75, 90],
			"translation": [0.25, 0, 0]
		},
		"fixed": {
			"rotation": [-77.49, -43.81, -81.24],
			"translation": [0, 0, -0.25]
		}
	},
	"groups": [
		{
			"name": "group",
			"origin": [0, 0, 0],
			"color": 0,
			"children": [0, 1, 2, 3, 4, 5, 6, 7, 8, 9, 10, 11, 12, 13, 14, 15, 16, 17, 18]
		}
	]
}